spark_rapids_pytools/__init__.py
spark_rapids_pytools/build.py
spark_rapids_pytools/wrapper.py
spark_rapids_pytools/cloud_api/__init__.py
spark_rapids_pytools/cloud_api/azurestorage.py
spark_rapids_pytools/cloud_api/databricks_aws.py
spark_rapids_pytools/cloud_api/databricks_aws_job.py
spark_rapids_pytools/cloud_api/databricks_azure.py
spark_rapids_pytools/cloud_api/databricks_azure_job.py
spark_rapids_pytools/cloud_api/dataproc.py
spark_rapids_pytools/cloud_api/dataproc_gke.py
spark_rapids_pytools/cloud_api/dataproc_gke_job.py
spark_rapids_pytools/cloud_api/dataproc_job.py
spark_rapids_pytools/cloud_api/emr.py
spark_rapids_pytools/cloud_api/emr_job.py
spark_rapids_pytools/cloud_api/gstorage.py
spark_rapids_pytools/cloud_api/onprem.py
spark_rapids_pytools/cloud_api/s3storage.py
spark_rapids_pytools/cloud_api/sp_types.py
spark_rapids_pytools/common/__init__.py
spark_rapids_pytools/common/cluster_inference.py
spark_rapids_pytools/common/exceptions.py
spark_rapids_pytools/common/prop_manager.py
spark_rapids_pytools/common/sys_storage.py
spark_rapids_pytools/common/utilities.py
spark_rapids_pytools/pricing/__init__.py
spark_rapids_pytools/pricing/databricks_aws_pricing.py
spark_rapids_pytools/pricing/databricks_azure_pricing.py
spark_rapids_pytools/pricing/dataproc_gke_pricing.py
spark_rapids_pytools/pricing/dataproc_pricing.py
spark_rapids_pytools/pricing/emr_pricing.py
spark_rapids_pytools/pricing/price_provider.py
spark_rapids_pytools/rapids/__init__.py
spark_rapids_pytools/rapids/bootstrap.py
spark_rapids_pytools/rapids/diagnostic.py
spark_rapids_pytools/rapids/profiling.py
spark_rapids_pytools/rapids/profiling_core.py
spark_rapids_pytools/rapids/qualification.py
spark_rapids_pytools/rapids/qualification_core.py
spark_rapids_pytools/rapids/qualification_stats.py
spark_rapids_pytools/rapids/rapids_job.py
spark_rapids_pytools/rapids/rapids_tool.py
spark_rapids_pytools/rapids/tool_ctxt.py
spark_rapids_pytools/rapids/dev/instance_description.py
spark_rapids_user_tools-25.12.2.dist-info/licenses/LICENSE
spark_rapids_user_tools-25.12.2.dist-info/METADATA
spark_rapids_user_tools-25.12.2.dist-info/WHEEL
spark_rapids_user_tools-25.12.2.dist-info/entry_points.txt
spark_rapids_user_tools-25.12.2.dist-info/top_level.txt
spark_rapids_user_tools-25.12.2.dist-info/RECORD
