Metadata-Version: 2.4
Name: spark-rapids-user-tools
Version: 25.12.2
Summary: A simple wrapper process around cloud service providers to run tools for the RAPIDS Accelerator for Apache Spark.
Author-email: NVIDIA Corporation <spark-rapids-support@nvidia.com>
License-Expression: Apache-2.0
Classifier: Programming Language :: Python :: 3
Classifier: Programming Language :: Python :: 3.10
Classifier: Programming Language :: Python :: 3.11
Classifier: Programming Language :: Python :: 3.12
Classifier: Operating System :: OS Independent
Requires-Python: <3.13,>=3.10
License-File: LICENSE
Requires-Dist: numpy>=2.2.6
Requires-Dist: chevron==0.14.0
Requires-Dist: fastprogress==1.0.3
Requires-Dist: fastcore==1.7.28
Requires-Dist: fire==0.7.1
Requires-Dist: pandas==2.3.0
Requires-Dist: pyYAML>=6.0.2
Requires-Dist: pyaml-env==1.2.2
Requires-Dist: tabulate==0.9.0
Requires-Dist: importlib-resources==6.5.2
Requires-Dist: requests==2.32.4
Requires-Dist: packaging==25.0
Requires-Dist: certifi==2025.6.15
Requires-Dist: urllib3==2.6.0
Requires-Dist: pygments==2.19.2
Requires-Dist: pydantic==2.11.7
Requires-Dist: pylint-pydantic==0.3.5
Requires-Dist: pyarrow==20.0.0
Requires-Dist: azure-storage-blob==12.25.1
Requires-Dist: adlfs==2024.12.0
Requires-Dist: progress==1.6.1
Requires-Dist: xgboost==3.0.2
Requires-Dist: shap==0.48.0
Requires-Dist: scikit-learn==1.7.0
Requires-Dist: psutil==7.0.0
Requires-Dist: pyspark<4.0.0,>=3.5.7
Requires-Dist: jproperties==2.1.2
Requires-Dist: optuna==4.4.0
Requires-Dist: optuna-integration==4.4.0
Provides-Extra: test
Requires-Dist: tox; extra == "test"
Requires-Dist: pytest; extra == "test"
Requires-Dist: pytest-cov; extra == "test"
Requires-Dist: cli_test_helpers; extra == "test"
Requires-Dist: behave; extra == "test"
Requires-Dist: flake8; extra == "test"
Requires-Dist: flake8-pydantic; extra == "test"
Requires-Dist: pylint==3.3.7; extra == "test"
Provides-Extra: qualx
Requires-Dist: holoviews; extra == "qualx"
Requires-Dist: matplotlib; extra == "qualx"
Requires-Dist: seaborn; extra == "qualx"
Provides-Extra: dev-env
Requires-Dist: tox; extra == "dev-env"
Requires-Dist: pytest; extra == "dev-env"
Requires-Dist: pytest-cov; extra == "dev-env"
Requires-Dist: cli_test_helpers; extra == "dev-env"
Requires-Dist: behave; extra == "dev-env"
Requires-Dist: flake8; extra == "dev-env"
Requires-Dist: flake8-pydantic; extra == "dev-env"
Requires-Dist: pylint==3.3.7; extra == "dev-env"
Requires-Dist: holoviews; extra == "dev-env"
Requires-Dist: matplotlib; extra == "dev-env"
Requires-Dist: seaborn; extra == "dev-env"
Dynamic: license-file
